odooapiclient/__init__.py
odooapiclient/auth.py
odooapiclient/client.py
odooapiclient/service_tools.py
samples/__init__.py
samples/example.py
odooapiclient-0.7.1.dist-info/LICENSE
odooapiclient-0.7.1.dist-info/METADATA
odooapiclient-0.7.1.dist-info/WHEEL
odooapiclient-0.7.1.dist-info/top_level.txt
odooapiclient-0.7.1.dist-info/RECORD
