Metadata-Version: 2.1
Name: odooapiclient
Version: 0.7.1
Summary: Odoo API Client
Home-page: https://github.com/andriisem/odoo-api-python-client.git
Author: Andrii Semko
Author-email: semko.andrey.i@gmail.com
License: UNKNOWN
Platform: UNKNOWN
Classifier: Programming Language :: Python
